githubctl/__init__.py
githubctl/cli/__init__.py
githubctl/cli/repo.py
githubctl/cli/user.py
githubctl/github.py
githubctl/main.py
githubctl/options.py
githubctl/utils.py
githubctl-0.1.7.dist-info/METADATA
githubctl-0.1.7.dist-info/WHEEL
githubctl-0.1.7.dist-info/entry_points.txt
githubctl-0.1.7.dist-info/RECORD
